cachio/__init__.py
cachio/cache.py
cachio/error.py
cachio/httpcache.py
cachio/redis_cache.py
cachio/utils.py
cachio-0.1.0.dist-info/METADATA
cachio-0.1.0.dist-info/WHEEL
cachio-0.1.0.dist-info/top_level.txt
cachio-0.1.0.dist-info/RECORD
