Metadata-Version: 2.4
Name: cachio
Version: 0.1.0
Summary: HTTP caching library for Python that supports in-memory and persistent storage, designed to speed up repeated requests and reduce redundant network calls.ea
Requires-Python: >=3.11
Requires-Dist: diskcache>=5.6.3
Requires-Dist: redis>=6.4.0
Requires-Dist: requests>=2.32.4
Requires-Dist: requests-toolbelt>=1.0.0
